<annotation>
    <folder> VOC2007 </folder>
    <filename>POD_1553.jpg</filename>
    <source>
        <database>Unknown</database>
    </source>
    <size>
        <width>1032</width>
        <height>1459</height>
        <depth>3</depth>
    </size>
    <segmented>0</segmented>
    <object>
        <name>figure</name>
        <pose>Unspecified</pose>
        <truncated>0</truncated>
        <difficult>0</difficult>
        <bndbox>
            <xmin>70</xmin>
            <ymin>92</ymin>
            <xmax>209</xmax>
            <ymax>230</ymax>
        </bndbox>
    </object>    <object>
        <name>figure</name>
        <pose>Unspecified</pose>
        <truncated>0</truncated>
        <difficult>0</difficult>
        <bndbox>
            <xmin>215</xmin>
            <ymin>92</ymin>
            <xmax>354</xmax>
            <ymax>229</ymax>
        </bndbox>
    </object>    <object>
        <name>figure</name>
        <pose>Unspecified</pose>
        <truncated>0</truncated>
        <difficult>0</difficult>
        <bndbox>
            <xmin>360</xmin>
            <ymin>92</ymin>
            <xmax>498</xmax>
            <ymax>227</ymax>
        </bndbox>
    </object>    <object>
        <name>formula</name>
        <pose>Unspecified</pose>
        <truncated>0</truncated>
        <difficult>0</difficult>
        <bndbox>
            <xmin>160</xmin>
            <ymin>359</ymin>
            <xmax>504</xmax>
            <ymax>397</ymax>
        </bndbox>
    </object>
</annotation>
